lighter_zoo/__init__.py
lighter_zoo/mixin.py
lighter_zoo/wrappers.py
lighter_zoo-0.1.3.dist-info/METADATA
lighter_zoo-0.1.3.dist-info/WHEEL
lighter_zoo-0.1.3.dist-info/top_level.txt
lighter_zoo-0.1.3.dist-info/RECORD
